{
  "id": "record-of-ragnarok",
  "type": "manga",
  "title": "Record of Ragnarok",
  "alt_titles": [
    "Shuumatsu no Valkyrie",
    "終末のワルキューレ"
  ],
  "source": "AniList",
  "source_id": 107098,
  "description": "The story begins when the gods call a conference to decide the whether to let humanity live or die, and settle on destroying humanity. But a lone valkyrie puts forward a suggestion to let the gods and humanity fight one last battle, as a last hope for humanity's continued survival. 13 gods will fight against 13 human champions in one-on-one battles to decide whether humanity lives or dies.\n\n(Source: Comikey)",
  "metadata": {
    "format": "MANGA",
    "status": "RELEASING",
    "startDate": "2017-11-25",
    "endDate": null,
    "genres": [
      "Action",
      "Drama",
      "Fantasy",
      "Supernatural"
    ],
    "averageScore": 78,
    "popularity": 63429,
    "chapters": null,
    "volumes": null
  },
  "images": [
    {
      "url": "https://s4.anilist.co/file/anilistcdn/media/manga/cover/medium/nx107098-zjO64Bc3Nrm5.jpg",
      "type": "cover",
      "source": "AniList"
    },
    {
      "url": "https://s4.anilist.co/file/anilistcdn/media/manga/banner/107098-kLSvW0gFkMok.jpg",
      "type": "banner",
      "source": "AniList"
    }
  ],
  "external_ids": {
    "anilist": 107098
  },
  "tags": [
    "Gods",
    "Mythology",
    "Death Game",
    "Survival",
    "Historical",
    "Super Power",
    "Seinen",
    "Primarily Adult Cast",
    "Female Protagonist",
    "Cultivation",
    "Gore"
  ],
  "updated_at": "2025-12-24T09:02:10.413Z",
  "created_at": "2025-12-22T22:01:20.547Z",
  "enriched": false
}