{
  "id": "demon-slayer-kimetsu-no-yaiba-the-movie-mugen-train",
  "type": "anime",
  "title": "Demon Slayer -Kimetsu no Yaiba- The Movie: Mugen Train",
  "alt_titles": [
    "Kimetsu no Yaiba: Mugen Ressha-hen",
    "鬼滅の刃 無限列車編"
  ],
  "source": "AniList",
  "source_id": 112151,
  "description": "This Demon Slayer movie sees Tanjiro Kamado and friends from the Demon Slayer corps board the Infinity Train on a new mission to investigate a mysterious series of disappearances, perpetrated by a demon who has been tormenting people and killing the demon slayers who oppose it.",
  "metadata": {
    "format": "MOVIE",
    "status": "FINISHED",
    "startDate": "2020-10-16",
    "endDate": "2020-10-16",
    "genres": [
      "Action",
      "Adventure",
      "Drama",
      "Fantasy",
      "Mystery",
      "Supernatural"
    ],
    "averageScore": 84,
    "popularity": 452723,
    "episodes": 1
  },
  "images": [
    {
      "url": "https://s4.anilist.co/file/anilistcdn/media/anime/cover/medium/bx112151-1qlQwPB1RrJe.png",
      "type": "cover",
      "source": "AniList"
    },
    {
      "url": "https://s4.anilist.co/file/anilistcdn/media/anime/banner/112151-eHCBz19nf2yC.jpg",
      "type": "banner",
      "source": "AniList"
    }
  ],
  "external_ids": {
    "anilist": 112151
  },
  "tags": [
    "Demons",
    "Swordplay",
    "Shounen",
    "Tragedy",
    "Trains",
    "Curses",
    "Male Protagonist",
    "Body Horror",
    "Super Power",
    "Monster Girl",
    "Primarily Teen Cast",
    "CGI",
    "Gore",
    "Primarily Male Cast",
    "Orphan",
    "Travel"
  ],
  "updated_at": "2025-12-23T01:21:41.774Z",
  "created_at": "2025-12-22T13:31:17.946Z",
  "enriched": false
}