{
  "id": "the-quintessential-quintuplets",
  "type": "manga",
  "title": "The Quintessential Quintuplets",
  "alt_titles": [
    "Go-toubun no Hanayome",
    "五等分の花嫁"
  ],
  "source": "AniList",
  "source_id": 100230,
  "description": "One day, a poor high school second-year named Futaro Uesugi comes across a private tutoring gig with good pay. But his pupils are his classmates!! And they’re quintuplets!! A-and they’re all gorgeous girls, but they’re also troublemakers who hate to study and are on the verge of flunking out! And his first task is simply gaining the sisters’ trust?! Every day is a party! The curtain is rising on the Nakano quintuplets’ quirky romantic comedy with five times the cute!!\n\n(Source: Kodansha USA)\n\nNote: Winner of the Shounen Manga category of the 43rd annual Kodansha Manga Awards.",
  "metadata": {
    "format": "MANGA",
    "status": "FINISHED",
    "startDate": "2017-08-09",
    "endDate": "2020-02-19",
    "genres": [
      "Comedy",
      "Drama",
      "Romance"
    ],
    "averageScore": 77,
    "popularity": 66206,
    "chapters": 122,
    "volumes": 14
  },
  "images": [
    {
      "url": "https://s4.anilist.co/file/anilistcdn/media/manga/cover/medium/nx100230-TA0RQ9d7RVas.jpg",
      "type": "cover",
      "source": "AniList"
    },
    {
      "url": "https://s4.anilist.co/file/anilistcdn/media/manga/banner/100230-aiEuOcHPAC9l.jpg",
      "type": "banner",
      "source": "AniList"
    }
  ],
  "external_ids": {
    "anilist": 100230
  },
  "tags": [
    "Twins",
    "Female Harem",
    "Primarily Female Cast",
    "Coming of Age",
    "Love Triangle",
    "Male Protagonist",
    "Heterosexual",
    "Marriage",
    "School",
    "Tsundere",
    "Shounen",
    "Family Life",
    "Cute Girls Doing Cute Things",
    "Ojou-sama"
  ],
  "updated_at": "2025-12-24T06:37:03.250Z",
  "created_at": "2025-12-22T21:59:47.976Z",
  "enriched": false
}