{
  "id": "gachiakuta",
  "type": "manga",
  "title": "Gachiakuta",
  "alt_titles": [
    "Gachiakuta",
    "ガチアクタ"
  ],
  "source": "AniList",
  "source_id": 144946,
  "description": "A boy lives in a floating town, where the poor scrape by and the rich live a sumptuous life, simply casting their garbage off the side, into the abyss. When he’s falsely accused of murder, though, his wrongful conviction leads to an unimaginable punishment—exile off the edge, with the rest of the trash. Down on the surface, the cast-off waste of humanity has bred vicious monsters, and to travel the path to vengeance against those who cast him into Hell, a boy will have to become a warrior…\n\n(Source: Kodansha USA)",
  "metadata": {
    "format": "MANGA",
    "status": "RELEASING",
    "startDate": "2022-02-16",
    "endDate": null,
    "genres": [
      "Action",
      "Drama",
      "Fantasy"
    ],
    "averageScore": 80,
    "popularity": 51678,
    "chapters": null,
    "volumes": null
  },
  "images": [
    {
      "url": "https://s4.anilist.co/file/anilistcdn/media/manga/cover/medium/bx144946-cscic3n2SwdY.jpg",
      "type": "cover",
      "source": "AniList"
    },
    {
      "url": "https://s4.anilist.co/file/anilistcdn/media/manga/banner/144946-85c80rNqlAPp.jpg",
      "type": "banner",
      "source": "AniList"
    }
  ],
  "external_ids": {
    "anilist": 144946
  },
  "tags": [
    "Ensemble Cast",
    "Shounen",
    "Male Protagonist",
    "Post-Apocalyptic",
    "Revenge",
    "Super Power",
    "Survival",
    "Dystopian",
    "Class Struggle",
    "Urban Fantasy",
    "Tragedy",
    "Assassins",
    "Primarily Male Cast",
    "Gods",
    "Urban"
  ],
  "updated_at": "2025-12-24T18:56:41.772Z",
  "created_at": "2025-12-24T18:56:41.772Z"
}