{
  "id": "march-comes-in-like-a-lion",
  "type": "manga",
  "title": "March Comes in Like a Lion",
  "alt_titles": [
    "3-gatsu no Lion",
    "3月のライオン"
  ],
  "source": "AniList",
  "source_id": 31224,
  "description": "Rei Kiriyama is a child prodigy. Rei Kiriyama is also an orphan who lives alone in an empty apartment. Rei Kiriyama is a teen working in an adult's world. Life is complicated for Rei. He's an up-and-coming shogi player on the verge of turning pro, but he has no homelife, or much of a life period, outside his board game, but thankfully with the help of some life-long friends he has an opportunity start all over again.\n\n(Source: DENPA)\n\nNotes:\n\n- Winner of the Grand Prize at the 4th Manga Taishou Award in 2011.\n\n- Winner of the 35th Kodansha Manga Award in 2011.\n\n- Winner of the Grand Prize at the Tezuka Osamu Cultural Prize in 2014.\n\n- Winner of the Grand Prize at the Japan Media Arts Festival in 2021.",
  "metadata": {
    "format": "MANGA",
    "status": "RELEASING",
    "startDate": "2007-07-13",
    "endDate": null,
    "genres": [
      "Drama",
      "Slice of Life"
    ],
    "averageScore": 87,
    "popularity": 31700,
    "chapters": null,
    "volumes": null
  },
  "images": [
    {
      "url": "https://s4.anilist.co/file/anilistcdn/media/manga/cover/medium/bx31224-dxugU08jahRT.jpg",
      "type": "cover",
      "source": "AniList"
    },
    {
      "url": "https://s4.anilist.co/file/anilistcdn/media/manga/banner/31224-7x74OyOI3qbj.jpg",
      "type": "banner",
      "source": "AniList"
    }
  ],
  "external_ids": {
    "anilist": 31224
  },
  "tags": [
    "Coming of Age",
    "Family Life",
    "Philosophy",
    "Rehabilitation",
    "Seinen",
    "Shogi",
    "Found Family",
    "Male Protagonist",
    "Bullying",
    "Iyashikei",
    "Board Game",
    "Food",
    "Heterosexual",
    "Tragedy"
  ],
  "updated_at": "2025-12-26T04:33:58.079Z",
  "created_at": "2025-12-26T04:33:58.079Z"
}